thumbhash/__init__.py
thumbhash/__main__.py
thumbhash/__version__.py
thumbhash/cli.py
thumbhash/decode.py
thumbhash/encode.py
thumbhash/hash.py
thumbhash/py.typed
thumbhash_python-1.0.1.dist-info/METADATA
thumbhash_python-1.0.1.dist-info/WHEEL
thumbhash_python-1.0.1.dist-info/entry_points.txt
thumbhash_python-1.0.1.dist-info/licenses/LICENSE
thumbhash_python-1.0.1.dist-info/RECORD
