Metadata-Version: 2.1
Name: thumbhash-python
Version: 1.0.1
Summary: A Python implementation of the Thumbhash image placeholder generation algorithm.
Project-URL: Documentation, https://github.com/Astropilot/thumbhash-python#readme
Project-URL: Issues, https://github.com/Astropilot/thumbhash-python/issues
Project-URL: Source, https://github.com/Astropilot/thumbhash-python
Author-email: Yohann MARTIN <contact@codexus.fr>
License-Expression: MIT
License-File: LICENSE
Classifier: Development Status :: 5 - Production/Stable
Classifier: Intended Audience :: Developers
Classifier: License :: OSI Approved :: MIT License
Classifier: Operating System :: OS Independent
Classifier: Programming Language :: Python
Classifier: Programming Language :: Python :: 3
Classifier: Programming Language :: Python :: 3 :: Only
Classifier: Programming Language :: Python :: 3.8
Classifier: Programming Language :: Python :: 3.9
Classifier: Programming Language :: Python :: 3.10
Classifier: Programming Language :: Python :: 3.11
Classifier: Programming Language :: Python :: 3.12
Classifier: Programming Language :: Python :: Implementation :: CPython
Classifier: Programming Language :: Python :: Implementation :: PyPy
Classifier: Topic :: Software Development
Classifier: Topic :: Software Development :: Libraries
Classifier: Topic :: Software Development :: Libraries :: Application Frameworks
Classifier: Topic :: Software Development :: Libraries :: Python Modules
Classifier: Typing :: Typed
Requires-Python: >=3.8
Requires-Dist: pillow<11.0.0,>=8.0.0
Requires-Dist: typer[all]<1.0.0,>=0.7.0
Provides-Extra: dev
Requires-Dist: coverage[toml]<8.0,>=6.5.0; extra == 'dev'
Requires-Dist: devtools[pygments]==0.12.2; extra == 'dev'
Requires-Dist: mypy==1.7.1; extra == 'dev'
Requires-Dist: pytest<8.0.0,>=7.1.3; extra == 'dev'
Requires-Dist: ruff==0.1.8; extra == 'dev'
Requires-Dist: types-pillow>=10.0.0; extra == 'dev'
